genio/__init__.py
genio/bot.py
genio/exceptions.py
genio/types.py
genio/utils.py
genio_telegram-0.1.1.dist-info/METADATA
genio_telegram-0.1.1.dist-info/WHEEL
genio_telegram-0.1.1.dist-info/top_level.txt
genio_telegram-0.1.1.dist-info/RECORD
