Metadata-Version: 2.1
Name: genio-telegram
Version: 0.1.1
Summary: A Gen Z-inspired Telegram MTProto API framework
Home-page: https://github.com/KunalG932/genio
Author: Kunal Gaikwad
Author-email: kunalgaikwad9322@gmail.com
Classifier: Development Status :: 3 - Alpha
Classifier: Intended Audience :: Developers
Classifier: License :: OSI Approved :: MIT License
Classifier: Operating System :: OS Independent
Classifier: Programming Language :: Python :: 3
Classifier: Programming Language :: Python :: 3.7
Classifier: Programming Language :: Python :: 3.8
Classifier: Programming Language :: Python :: 3.9
Classifier: Programming Language :: Python :: 3.10
Classifier: Topic :: Software Development :: Libraries :: Python Modules
Classifier: Topic :: Communications :: Chat
Requires-Python: >=3.7
Requires-Dist: aiohttp>=3.8.0
Requires-Dist: python-dotenv>=0.19.0
Requires-Dist: typing-extensions>=4.0.0
